baseopt/__init__.py
baseopt/options.py
baseopt-0.1.3.dist-info/LICENSE
baseopt-0.1.3.dist-info/METADATA
baseopt-0.1.3.dist-info/WHEEL
baseopt-0.1.3.dist-info/top_level.txt
baseopt-0.1.3.dist-info/RECORD
