Metadata-Version: 2.1
Name: baseopt
Version: 0.1.3
Summary: A package for parsing and managing CLI options/arguments from getopt.
Author-email: An Wang <wangan.cs@gmail.com>
License: MIT License
Project-URL: Repository, https://github.com/alephpiece/baseopt
License-File: LICENSE
